spookify/__init__.py
spookify/__main__.py
spookify/wordlists/festive.json
spookify/wordlists/spooky.json
spookify-0.3.2.post1.dist-info/LICENSE
spookify-0.3.2.post1.dist-info/METADATA
spookify-0.3.2.post1.dist-info/WHEEL
spookify-0.3.2.post1.dist-info/entry_points.txt
spookify-0.3.2.post1.dist-info/top_level.txt
spookify-0.3.2.post1.dist-info/RECORD
