Metadata-Version: 2.1
Name: spookify
Version: 0.3.2.post1
Summary: Pun generator
Home-page: https://github.com/georgewatson/spookify
Author: George Watson
Author-email: george@georgewatson.me
License: MIT
Platform: UNKNOWN
Classifier: License :: OSI Approved :: MIT License
Classifier: Programming Language :: Python :: 3.5
Classifier: Topic :: Text Processing :: Linguistic
Requires-Dist: jellyfish
Requires-Dist: regex
